par_term_emu_core_rust/__init__.py
par_term_emu_core_rust/_native.cpython-314-darwin.so
par_term_emu_core_rust/debug.py
par_term_emu_core_rust-0.25.0.dist-info/METADATA
par_term_emu_core_rust-0.25.0.dist-info/WHEEL
par_term_emu_core_rust-0.25.0.dist-info/licenses/LICENSE
par_term_emu_core_rust-0.25.0.dist-info/RECORD
