Metadata-Version: 2.4
Name: par-term-emu-core-rust
Version: 0.25.0
Classifier: License :: OSI Approved :: MIT License
Classifier: Environment :: Console
Classifier: Development Status :: 4 - Beta
Classifier: Intended Audience :: Developers
Classifier: Programming Language :: Python :: 3
Classifier: Programming Language :: Python :: 3.12
Classifier: Programming Language :: Python :: 3.13
Classifier: Programming Language :: Python :: 3.14
Classifier: Programming Language :: Rust
Classifier: Operating System :: POSIX :: Linux
Classifier: Operating System :: MacOS
Classifier: Operating System :: Microsoft :: Windows :: Windows 10
Classifier: Operating System :: Microsoft :: Windows :: Windows 11
Classifier: Topic :: Terminals
Classifier: Topic :: Terminals :: Terminal Emulators/X Terminals
Classifier: Topic :: Software Development :: Libraries :: Python Modules
Classifier: Typing :: Typed
Requires-Dist: pillow>=12.1.0
Requires-Dist: pillow>=12.1.0 ; extra == 'image'
Provides-Extra: image
License-File: LICENSE
Summary: A comprehensive terminal emulator library in Rust with Python bindings - supports true color, alt screen, mouse reporting, bracketed paste, and full Unicode
Keywords: terminal,emulator,vt100,vt220,vt320,vt420,ansi,sixel,pty,rust,pyo3,terminal-emulator,unicode,true-color
Home-Page: https://github.com/paulrobello/par-term-emu-core-rust
Author-email: Paul Robello <probello@gmail.com>
Maintainer-email: Paul Robello <probello@gmail.com>
Requires-Python: >=3.12
Project-URL: Discussions, https://github.com/paulrobello/par-term-emu-core-rust/discussions
Project-URL: Documentation, https://github.com/paulrobello/par-term-emu-core-rust/blob/main/README.md
Project-URL: Homepage, https://github.com/paulrobello/par-term-emu-core-rust
Project-URL: Issues, https://github.com/paulrobello/par-term-emu-core-rust/issues
Project-URL: Repository, https://github.com/paulrobello/par-term-emu-core-rust
